laoshi/__init__.py
laoshi/converter.py
laoshi/deckmanager.py
laoshi/flashcardgenerator.py
laoshi/main.py
laoshi/speaker.py
laoshi/translator.py
laoshi-0.6.4.dist-info/licenses/LICENSE
laoshi-0.6.4.dist-info/METADATA
laoshi-0.6.4.dist-info/WHEEL
laoshi-0.6.4.dist-info/entry_points.txt
laoshi-0.6.4.dist-info/top_level.txt
laoshi-0.6.4.dist-info/RECORD
