Metadata-Version: 2.4
Name: laoshi
Version: 0.6.4
Summary: CLI application for learning Chinese.
Author-email: Ruben Serradas <ruben@serradas.org>
Requires-Python: <4.0,>=3.10
License-File: LICENSE
Requires-Dist: pypinyin<1.0.0,>=0.50.0
Requires-Dist: googletrans==4.0.2
Requires-Dist: gtts<3.0.0,>=2.5.0
Requires-Dist: genanki<1.0.0,>=0.13.1
Requires-Dist: requests<3.0.0,>=2.31.0
Requires-Dist: click<9.0.0,>=8.1.7
Requires-Dist: starcc<1.0.0,>=0.0.5
Requires-Dist: click-repl<1.0.0,>=0.3.0
Dynamic: license-file
